slacktokens.py
slacktokens-0.2.6.dist-info/licenses/LICENSE
slacktokens-0.2.6.dist-info/METADATA
slacktokens-0.2.6.dist-info/WHEEL
slacktokens-0.2.6.dist-info/top_level.txt
slacktokens-0.2.6.dist-info/RECORD
