Metadata-Version: 2.4
Name: slacktokens
Version: 0.2.6
Summary: Extract personal tokens and authentication cookie from the Slack app
Author-email: Heath Raftery <heath@empirical.ee>
Project-URL: Repository, https://github.com/hraftery/slacktokens
Classifier: Development Status :: 4 - Beta
Classifier: Environment :: Console
Classifier: Programming Language :: Python :: 3
Classifier: Programming Language :: Python :: 3.7
Classifier: Intended Audience :: Developers
Classifier: License :: OSI Approved :: GNU General Public License v3 (GPLv3)
Classifier: Topic :: Software Development :: Libraries
Classifier: Topic :: Utilities
Requires-Python: <3.12,>=3.7
License-File: LICENSE
Requires-Dist: leveldb==0.201
Requires-Dist: pycookiecheat
Dynamic: license-file
